LICENSE
megamock/__init__.py
megamock/import_machinery.py
megamock/import_references.py
megamock/import_types.py
megamock/megamocks.py
megamock/megapatches.py
megamock/megas.py
megamock/name_words.py
megamock/plugins/__init__.py
megamock/plugins/pytest.py
megamock/py.typed
megamock/type_util.py
megamock-0.1.0b11.dist-info/LICENSE
megamock-0.1.0b11.dist-info/METADATA
megamock-0.1.0b11.dist-info/WHEEL
megamock-0.1.0b11.dist-info/RECORD
