Metadata-Version: 2.1
Name: megamock
Version: 0.1.0b11
Summary: Mega mocking capabilities - stop using dot-notated paths!
Home-page: https://github.com/JamesHutchison/megamock
License: MIT
Keywords: mock,test
Author: James Hutchison
Author-email: jamesghutchison@proton.me
Requires-Python: >=3.10,<4.0
Classifier: Development Status :: 3 - Alpha
Classifier: License :: OSI Approved :: MIT License
Classifier: Operating System :: OS Independent
Classifier: Programming Language :: Python :: 3
Classifier: Programming Language :: Python :: 3.10
Classifier: Programming Language :: Python :: 3.11
Classifier: Programming Language :: Python :: 3.12
Classifier: Topic :: Software Development :: Libraries :: Python Modules
Classifier: Topic :: Software Development :: Testing
Classifier: Topic :: Software Development :: Testing :: Mocking
Requires-Dist: asttokens (>=2.2.1,<2.3.0)
Requires-Dist: varname[asttokens] (>=0.10.0,<0.11.0)
Project-URL: Repository, https://github.com/JamesHutchison/megamock
